{
    "name": 38,
    "url": 26,
    "q": 15,
    "Name": 14,
    "Title": 12,
    "email": 12,
    "filename": 11,
    "title": 11,
    "description": 11,
    "href": 9,
    "username": 8,
    "file": 8,
    "SAMLResponse": 8,
    "src": 8,
    "Description": 7,
    "value": 6,
    "content": 6,
    "user": 6,
    "r": 6,
    "search": 6,
    "data": 6,
    "referer": 6,
    "Referer": 6,
    "style": 6,
    "query": 5,
    "message": 5,
    "s": 5,
    "password": 5,
    "id": 5,
    "p": 5,
    "where": 5,
    "redirect": 5,
    "error": 5,
    "callback": 5,
    "class": 4,
    "type": 4,
    "text": 4,
    "c": 4,
    "utm_campaign": 4,
    "what": 4,
    "onmouseover": 4,
    "pathname": 4,
    "target": 4,
    "a": 4,
    "onclick": 4,
    "Search": 4,
    "Body": 4,
    "lang": 3,
    "path": 3,
    "html": 3,
    "term": 3,
    "URL": 3,
    "onIgnoreTag": 3,
    "ad_type": 3,
    "Subject": 3,
    "utm_source": 3,
    "author": 3,
    "tags": 3,
    "issues": 3,
    "ctx": 2,
    "atb": 2,
    "endpoint": 2,
    "status": 2,
    "redirect_uri": 2,
    "vote": 2,
    "Nickname": 2,
    "dir": 2,
    "back": 2,
    "city": 2,
    "location": 2,
    "params": 2,
    "u": 2,
    "readyFunction": 2,
    "Comments": 2,
    "auth": 2,
    "militarybranch": 2,
    "__proto__": 2,
    "category": 2,
    "label": 2,
    "language_id": 2,
    "cvo_sid1": 2,
    "state": 2,
    "action": 2,
    "Format": 2,
    "flaw": 2,
    "e": 2,
    "t": 2,
    "currency": 2,
    "Cookie": 2,
    "return": 2,
    "onerror": 2,
    "color": 2,
    "data-original": 2,
    "other": 2,
    "view": 2,
    "Company": 2,
    "Host": 2,
    "subject": 2,
    "X-Forwarded-Host": 2,
    "return_url": 2,
    "sequel": 2,
    "utm_medium": 2,
    "users": 2,
    "admin": 2,
    "shop": 2,
    "varCoveoSearchResultPageURL": 1,
    "varDocumentReferrer": 1,
    "varStaticCoveoSearchResultPageURL": 1,
    "referrer": 1,
    "myk": 1,
    "CoveoSearchUrl": 1,
    "PageLink": 1,
    "ResponseHandlingLanguage": 1,
    "UID": 1,
    "snapcode": 1,
    "attribute": 1,
    "domain": 1,
    "script_name": 1,
    "viewer_url": 1,
    "auth_code": 1,
    "cID": 1,
    "phone": 1,
    "submitted": 1,
    "g-recaptcha-response": 1,
    "_ga": 1,
    "additional_text": 1,
    "use": 1,
    "SVG": 1,
    "js-topbar": 1,
    "js-share-link": 1,
    "QUERY_STRING": 1,
    "GameplayVersion": 1,
    "statsBreakdown": 1,
    "posttitle": 1,
    "strSearch": 1,
    "token": 1,
    "channels": 1,
    "initial_comment": 1,
    "usernames": 1,
    "dimension1": 1,
    "set": 1,
    "Document": 1,
    "destpage": 1,
    "imgId": 1,
    "fld_frompor": 1,
    "unsafe-inline": 1,
    "unsafe-eval": 1,
    "v0sjx": 1,
    "uyvvr": 1,
    "date": 1,
    "OprId": 1,
    "updater-secret-input": 1,
    "crumb": 1,
    "transactionName": 1,
    "cookie_swa_lang": 1,
    "author_url": 1,
    "movieName": 1,
    "Location": 1,
    "Content-Type": 1,
    "X-XSS-Protection": 1,
    "gapup_login_nonce": 1,
    "stripping": 1,
    "lang_id": 1,
    "segFilter": 1,
    "xss": 1,
    "postMessage": 1,
    "WhatSubmitted": 1,
    "Network": 1,
    "msg": 1,
    "autolink": 1,
    "parentPageString": 1,
    "labelsString": 1,
    "fsNewText": 1,
    "msgBody": 1,
    "formaction": 1,
    "c4": 1,
    "rcnum": 1,
    "numSuggestions": 1,
    "Ctg": 1,
    "original_referer": 1,
    "option": 1,
    "section": 1,
    "arg2": 1,
    "CKEditorFuncNum": 1,
    "billing-address": 1,
    "tier": 1,
    "BIO": 1,
    "LOCATION": 1,
    "test": 1,
    "payload": 1,
    "lineItems": 1,
    "requires_python": 1,
    "ahoy_visitor": 1,
    "ahoy_visit": 1,
    "image": 1,
    "image_width": 1,
    "image_height": 1,
    "q_21675": 1,
    "ts": 1,
    "handle": 1,
    "_regionConfirm_": 1,
    "asset": 1,
    "ms": 1,
    "X-XSRF-TOKEN": 1,
    "win": 1,
    "Asset": 1,
    "edit": 1,
    "download_url": 1,
    "home_page": 1,
    "locationId": 1,
    "parameters": 1,
    "Message": 1,
    "mult-tag": 1,
    "css": 1,
    "breakdown": 1,
    "section_tab": 1,
    "lastname": 1,
    "NAME": 1,
    "fileName": 1,
    "editor": 1,
    "rendermode": 1,
    "backLink": 1,
    "Error": 1,
    "assets": 1,
    "Group": 1,
    "data-controller": 1,
    "scripts": 1,
    "myFolder": 1,
    "Request-URI": 1,
    "free_word": 1,
    "service": 1,
    "flashcookie": 1,
    "F1607675": 1,
    "continue": 1,
    "signup_continue": 1,
    "YOUR_BUCKET_NAME": 1,
    "YOUR_FILE_NAME": 1,
    "genesis_id": 1,
    "lf-content": 1,
    "js-xss": 1,
    "shop_domain": 1,
    "platform": 1,
    "hmac": 1,
    "login": 1,
    "fromsource": 1,
    "background-image": 1,
    "data-title": 1,
    "svg": 1,
    "math": 1,
    "kxsrc": 1,
    "height": 1,
    "spay_formatted_price": 1,
    "spay_price": 1,
    "spay_currency": 1,
    "caption": 1,
    "gnar_containerId": 1,
    "grauth": 1,
    "checkoutButton": 1,
    "organization": 1,
    "thumbnail_url": 1,
    "number": 1,
    "recipient": 1,
    "muber-id": 1,
    "norw": 1,
    "padding": 1,
    "kubernetesNamespace": 1,
    "flow": 1,
    "profile_id": 1,
    "fullname": 1,
    "clan_id": 1,
    "comment": 1,
    "terminalId": 1,
    "chart_title": 1,
    "FirstName": 1,
    "bk": 1,
    "pr_zip_location": 1,
    "kramed": 1,
    "recipe_url": 1,
    "note_html": 1,
    "cached_markdown_version": 1,
    "leverParameter": 1,
    "question": 1,
    "userId": 1,
    "payload_json": 1,
    "pagePath": 1,
    "data-disable-with": 1,
    "_shipping_state": 1,
    "_billing_state": 1,
    "Variants": 1,
    "link777": 1,
    "wishlistComment": 1,
    "nrnew-interval": 1,
    "page": 1,
    "n": 1,
    "hookName": 1,
    "hookFunction": 1,
    "1139": 1,
    "q_21677": 1,
    "company": 1,
    "skill_name": 1,
    "build": 1,
    "channel": 1,
    "Signature": 1,
    "highlighterId": 1,
    "color_scheme": 1,
    "x": 1,
    "links": 1,
    "advanced_val": 1,
    "vendor_description": 1,
    "failure_message": 1,
    "User-Agent": 1,
    "udi-id": 1,
    "Etunimi": 1,
    "S\u00e4hk\u00f6posti": 1,
    "County": 1,
    "afterReload": 1,
    "MailboxStatusAutoCall": 1,
    "xtl_amount_type": 1,
    "xtl_coupon_code": 1,
    "xtl_amount": 1,
    "period_preset": 1,
    "comment_body": 1,
    "ionUrl": 1,
    "addKeyBinding": 1,
    "SearchDomain": 1,
    "city_id": 1,
    "comments": 1,
    "authorization_endpoint": 1,
    "installation_id": 1,
    "errorMessage": 1,
    "Category": 1,
    "section_type": 1,
    "iframe": 1,
    "subscribeNonce": 1,
    "prefixRank": 1,
    "bookmarkPageId": 1,
    "txHash": 1,
    "hostname": 1,
    "DIFFICULT": 1,
    "uid": 1,
    "xxslots": 1,
    "configUrl": 1,
    "success_url": 1,
    "decline_url": 1,
    "mktoResponse": 1,
    "for": 1,
    "formId": 1,
    "followUpUrl": 1,
    "upaHandle": 1,
    "upaName": 1,
    "fontFamily": 1,
    "extraData": 1,
    "signup_type": 1,
    "auth_url": 1,
    "cookieName": 1,
    "stickerId": 1,
    "photoUrls": 1,
    "condition_name": 1,
    "v": 1,
    "loc": 1,
    "collection": 1,
    "LocaleID": 1,
    "cName": 1,
    "setPerPage": 1,
    "item": 1,
    "data-placeholder": 1,
    "archive": 1,
    "frm_email": 1,
    "trg": 1,
    "website": 1,
    "is_private": 1,
    "f": 1,
    "rhsearch": 1,
    "data_url": 1,
    "bgcolor": 1,
    "error_description": 1,
    "error_hint": 1,
    "Disliked_reviewers": 1,
    "Liked_reviewers": 1,
    "Reasons": 1,
    "subid_": 1,
    "title_": 1,
    "answers": 1,
    "buttonText": 1,
    "buttonImageURL": 1,
    "buttonTextStyle": 1,
    "buttonAction": 1,
    "buttonCursor": 1,
    "advertiser": 1,
    "data-sourcepos": 1,
    "Content": 1,
    "staticDomainName": 1,
    "succUrl": 1,
    "onload": 1,
    "MD": 1,
    "source_branch": 1,
    "autoplay": 1,
    "emailbody": 1,
    "js": 1,
    "data-site-root": 1,
    "data-locale-root": 1,
    "poc": 1,
    "o": 1,
    "submit": 1,
    "widget-IDs": 1,
    "XXX": 1,
    "-back": 1,
    "prefn1": 1,
    "prefv1": 1,
    "address": 1,
    "exec": 1,
    "val": 1,
    "repo": 1,
    "K\u00e4ytt\u00e4j\u00e4tunnus": 1,
    "relsexp": 1,
    "image_upload": 1,
    "random": 1,
    "again": 1,
    "site_index": 1,
    "encodedForm": 1,
    "accesskey": 1,
    "video_id": 1,
    "NEW_RELIC_LABELS": 1,
    "contextPath": 1,
    "receipt": 1,
    "theme_handle": 1,
    "next_url": 1,
    "ss_country_filter": 1,
    "Content-Length": 1,
    "photoUrl": 1,
    "timestamp": 1,
    "HumanTime": 1,
    "plot": 1,
    "trazilica": 1,
    "Labels": 1,
    "iceID": 1,
    "internalPath": 1,
    "REPORT_URL": 1,
    "EMOTICON_URL": 1,
    "WIDTH": 1,
    "HEIGHT": 1,
    "Content-Disposition": 1,
    "jaw": 1,
    "CFID": 1,
    "tax": 1,
    "Lang": 1,
    "siteBaseUrl": 1,
    "refresh": 1,
    "cfg": 1,
    "zzz": 1,
    "ReturnUrl": 1,
    "with_tags_data": 1,
    "urlStr": 1,
    "events_per_page": 1,
    "creator_redirect": 1,
    "permalink": 1,
    "wish_list": 1,
    "Comment": 1,
    "sort_col": 1,
    "doAuthenticate": 1,
    "request": 1,
    "registrations": 1,
    "select": 1,
    "signup": 1,
    "cdn_url": 1,
    "button-bg-color": 1,
    "_landing_page": 1,
    "return_to": 1,
    "bgColor": 1,
    "mail": 1,
    "search_query": 1,
    "Accounts_Admin_Email_Approval_Needed_With_Reason_Default": 1,
    "font": 1,
    "77d50": 1,
    "code": 1,
    "Who-Platform": 1,
    "data-remote": 1,
    "data-method": 1,
    "data-type": 1,
    "blkCatIds": 1,
    "fld_displaytype": 1,
    "kp": 1,
    "kae": 1,
    "mode": 1,
    "alias": 1,
    "tooltip": 1,
    "media_url": 1,
    "metro": 1,
    "sysparm_channelID": 1,
    "indicatorsFile": 1,
    "review": 1,
    "keywords": 1,
    "post_title": 1,
    "project": 1,
    "subcat": 1,
    "serial": 1,
    "scribe_context": 1,
    "next": 1,
    "q_13779": 1,
    "remember_me": 1,
    "new-d1": 1,
    "__zopim_widget_proxy": 1,
    "triager": 1,
    "hacker": 1,
    "c-detail__user": 1,
    "google_apps_uri": 1,
    "reference": 1,
    "access_token": 1,
    "Data": 1,
    "more": 1,
    "ajx2q": 1,
    "sendData": 1,
    "extcss": 1,
    "add-title": 1,
    "config": 1,
    "Nimesi": 1,
    "iface": 1,
    "applicationName": 1,
    "back_to": 1,
    "txt": 1,
    "agreeTerms": 1,
    "acceptTermsErrorMessage": 1,
    "reason": 1,
    "cpID": 1,
    "__e2e_action_id": 1,
    "window_id": 1,
    "redirect_to": 1,
    "company_name": 1,
    "trn": 1,
    "version": 1,
    "6177527534dc114eb07fa829e4ce4d28": 1,
    "problems_text": 1,
    "originalUrl": 1,
    "miniUrl": 1,
    "page_search_query": 1,
    "utm_content": 1,
    "authorName": 1,
    "image_src": 1,
    "language": 1,
    "Suite": 1,
    "international": 1,
    "5": 1,
    "reblog": 1,
    "hotbox": 1,
    "agecheck": 1,
    "api": 1,
    "subscribe": 1,
    "all": 1,
    "article": 1,
    "tasks": 1,
    "read": 1,
    "nav": 1,
    "Job": 1,
    "etc": 1,
    "kinetic": 1,
    "analytics": 1,
    "profile": 1
}